music_validator_micro/__init__.py
music_validator_micro/_database.py
music_validator_micro/_file.py
music_validator_micro/_generic_tag_map.py
music_validator_micro/_music_file.py
music_validator_micro/_tag.py
music_validator_micro/music_validator.py
music_validator_micro-0.1.14.dist-info/METADATA
music_validator_micro-0.1.14.dist-info/WHEEL
music_validator_micro-0.1.14.dist-info/licenses/LICENSE
music_validator_micro-0.1.14.dist-info/RECORD
